stoneredis/__init__.py
stoneredis/client.py
stoneredis-0.6.1.dist-info/top_level.txt
stoneredis-0.6.1.dist-info/METADATA
stoneredis-0.6.1.dist-info/DESCRIPTION.rst
stoneredis-0.6.1.dist-info/metadata.json
stoneredis-0.6.1.dist-info/WHEEL
stoneredis-0.6.1.dist-info/RECORD
