Metadata-Version: 2.0
Name: stoneredis
Version: 0.6.1
Summary: Redis client based on redis-py client with some added features
Home-page: https://github.com/stoneworksolutions/stoneredis
Author: Pedro Ten
Author-email: pedroten@gmail.com
License: ISCL
Keywords: stoneredis
Platform: UNKNOWN
Classifier: Development Status :: 2 - Pre-Alpha
Classifier: Intended Audience :: Developers
Classifier: License :: OSI Approved :: ISC License (ISCL)
Classifier: Natural Language :: English
Classifier: Programming Language :: Python :: 2
Classifier: Programming Language :: Python :: 2.6
Classifier: Programming Language :: Python :: 2.7
Classifier: Programming Language :: Python :: 3
Classifier: Programming Language :: Python :: 3.3
Classifier: Programming Language :: Python :: 3.4
Classifier: Programming Language :: Python :: 3.5
Requires-Dist: redis (==2.10.3)
Requires-Dist: python-redis-lock[django] (==2.3.0)
